pyldpc/__init__.py
pyldpc/codingfunctions.py
pyldpc/decodingfunctions.py
pyldpc/imagesformat.py
pyldpc/ldpc_images.py
pyldpc/ldpc_sound.py
pyldpc/ldpcalgebra.py
pyldpc/ldpcmatrices.py
pyldpc/soundformat.py
pyldpc-0.7.6.dist-info/DESCRIPTION.rst
pyldpc-0.7.6.dist-info/METADATA
pyldpc-0.7.6.dist-info/RECORD
pyldpc-0.7.6.dist-info/WHEEL
pyldpc-0.7.6.dist-info/metadata.json
pyldpc-0.7.6.dist-info/top_level.txt
