Metadata-Version: 2.0
Name: pyldpc
Version: 0.7.6
Summary: Simulation of Low Density Parity Check Codes ldpc
Home-page: https://github.com/hichamjanati/pyldpc
Author: Hicham Janati
Author-email: hicham.janati@ensae.fr
License: MIT
Keywords: codes ldpc error detection decoding coding pyldpc
Platform: UNKNOWN
Classifier: Programming Language :: Python :: 2.7
Classifier: Programming Language :: Python :: 3.5
Classifier: Development Status :: 4 - Beta
Classifier: Environment :: MacOS X
Classifier: Framework :: IPython
Classifier: Intended Audience :: Developers
Classifier: Intended Audience :: Education
Classifier: Intended Audience :: Science/Research
Classifier: Intended Audience :: Telecommunications Industry
Classifier: Natural Language :: English
Classifier: Natural Language :: French
Requires-Dist: numpy
Requires-Dist: scipy
